get_fshare/__init__.py
get_fshare/get_fshare.py
get_fshare/test_function.py
get_fshare/z.py
get_fshare-2.3.3.dist-info/LICENSE
get_fshare-2.3.3.dist-info/METADATA
get_fshare-2.3.3.dist-info/WHEEL
get_fshare-2.3.3.dist-info/top_level.txt
get_fshare-2.3.3.dist-info/RECORD
