Metadata-Version: 2.1
Name: get-fshare
Version: 2.3.3
Summary: Python lib to get link Fshare.vn
Home-page: http://github.com/tudoanh/get_fshare
Author: Do Anh Tu
Author-email: tu0703@gmail.com
License: MIT
Platform: UNKNOWN
Requires-Python: >=3.5
